zyte_api/__init__.py
zyte_api/convertor.py
zyte_api_convertor-1.0.3.dist-info/LICENSE
zyte_api_convertor-1.0.3.dist-info/METADATA
zyte_api_convertor-1.0.3.dist-info/WHEEL
zyte_api_convertor-1.0.3.dist-info/entry_points.txt
zyte_api_convertor-1.0.3.dist-info/top_level.txt
zyte_api_convertor-1.0.3.dist-info/RECORD
