Metadata-Version: 2.1
Name: zyte-api-convertor
Version: 1.0.3
Summary: A simple python module for Zyte Scrapy ZyteAPI projects
Home-page: https://github.com/mukthy/zyte_api_convertor
Author: Mukthy
Author-email: muktheeswaran.m@gmail.com
Project-URL: Bug Tracker, https://github.com/mukthy/zyte_api_convertor/-/issues
Project-URL: repository, https://github.com/mukthy/zyte_api_convertor
Classifier: Programming Language :: Python :: 3
Classifier: License :: OSI Approved :: MIT License
Classifier: Operating System :: OS Independent
Requires-Python: >=3.6
License-File: LICENSE
Requires-Dist: packaging
Requires-Dist: scrapy
Requires-Dist: zyte-api
Requires-Dist: scrapy-zyte-api
Requires-Dist: black
